anthemav/__init__.py
anthemav/connection.py
anthemav/protocol.py
anthemav/tools.py
anthemav-1.3.0.dist-info/LICENSE
anthemav-1.3.0.dist-info/METADATA
anthemav-1.3.0.dist-info/WHEEL
anthemav-1.3.0.dist-info/entry_points.txt
anthemav-1.3.0.dist-info/top_level.txt
anthemav-1.3.0.dist-info/zip-safe
anthemav-1.3.0.dist-info/RECORD
