Metadata-Version: 2.1
Name: anthemav
Version: 1.3.0
Summary: Python API for controlling Anthem Receivers
Home-page: https://github.com/nugget/python-anthemav
Author: David McNett
Author-email: nugget@macnugget.org
License: LICENSE
Platform: UNKNOWN
Classifier: Development Status :: 5 - Production/Stable
Classifier: Intended Audience :: Developers
Classifier: License :: OSI Approved :: MIT License
Classifier: Operating System :: OS Independent
Classifier: Programming Language :: Python
Classifier: Topic :: Software Development :: Libraries :: Python Modules
